{
  "id": "nankyoku-ryorinin",
  "title": "南極料理人",
  "title_original": "南極料理人",
  "author": "",
  "reader_persona": "gura",
  "status": "reading",
  "progress": {
    "current_chapter": 5,
    "last_read": "2026-07-02",
    "bookmark_note": "全片看畢(結局歸國+變回普通大叔+家的圓+片尾沙灘排球彩蛋);觀看限制=ScreenStream縮圖牆觀看、字幕靠OCR、時間軸非官方;重點:西村(揣女兒友花乳牙)/本山(45歲家裂痕)/福田(歸國馬拉松)/拉麵救贖+極光vs拉麵題眼/電話戀愛清水;收播後接看Morten Rustad挪威風景片(峽灣極光雪山水下企鵝水母)"
  },
  "characters": [
    "kawamura",
    "hirabayashi",
    "nishimura",
    "nishihira",
    "fukuda",
    "kaneda",
    "mikoshiba",
    "motoyama",
    "nishimura-family",
    "suzuki"
  ],
  "origin": "imported",
  "tags": [
    "電影",
    "日影",
    "觀影心得",
    "stream-watch",
    "喜劇",
    "美食"
  ]
}
